{
    "openapi": "3.1.0",
    "info": {
        "title": "POS",
        "version": "2.0",
        "summary": "fetch products of pos",
        "contact": {
            "name": "Alaa Alsalehi",
            "email": "alaadiaa@gmail.com"
        }
    },
    "servers": [
        {
            "url": "http://thepos.test/",
            "description": "thePOS test server"
        }
    ],
    "paths": {
        "/api/v2/products": {
            "get": {
                "summary": "Get products",
                "operationId": "ProductController@index",
                "responses": {
                    "200": {
                        "description": "OK",
                        "content": {
                            "application/json": {
                                "schema": {
                                    "$ref": "#/components/schemas/ProductPaginator"
                                },
                                "examples": {
                                    "example-1": {
                                        "value": {
                                            "data": [
                                                {
                                                    "sku": "72527273070",
                                                    "name": "UPCA prodcut",
                                                    "price": 100,
                                                    "tax_rate": 10,
                                                    "taxed_price": 110,
                                                    "image": "https://pixnio.com/media/perfume-fancy-product-package-wedding-ring",
                                                    "product_group": {
                                                        "id": 10,
                                                        "name": "products",
                                                        "parent": 1,
                                                        "is_group": false,
                                                        "disabled": true
                                                    },
                                                    "sale_price": 75,
                                                    "taxed_sale_price": 82.5,
                                                    "quantity": 0,
                                                    "available": false
                                                }
                                            ],
                                            "links": {
                                                "links": {
                                                    "first": "http://thepos.test/api/v1/products?page=1",
                                                    "last": "http://thepos.test/api/v1/products?page=1"
                                                }
                                            },
                                            "meta": {
                                                "current_page": 1,
                                                "from": 1,
                                                "last_page": 1,
                                                "path": "http://thepos.test/api/v1/products",
                                                "per_page": 15,
                                                "to": 5,
                                                "total": 5
                                            }
                                        }
                                    }
                                }
                            }
                        }
                    },
                    "401": {
                        "$ref": "#/components/responses/Error"
                    }
                },
                "parameters": [
                    {
                        "schema": {
                            "type": "integer"
                        },
                        "in": "query",
                        "name": "page",
                        "description": "page number"
                    },
                    {
                        "schema": {
                            "type": "number"
                        },
                        "in": "query",
                        "name": "group",
                        "description": "fetch only products of that category"
                    }
                ]
            },
            "parameters": []
        },
        "/api/v2/product-groups": {
            "get": {
                "summary": "Get Product Groups",
                "operationId": "ProductGroupsController@index",
                "responses": {
                    "200": {
                        "description": "OK",
                        "content": {
                            "application/json": {
                                "schema": {
                                    "$ref": "#/components/schemas/ProductPaginator"
                                },
                                "examples": {
                                    "example-1": {
                                        "value": {
                                            "data": [
                                                {
                                                    "sku": "978020137962",
                                                    "name": "ean13 product",
                                                    "price": 10,
                                                    "tax_rate": 15,
                                                    "taxed_price": 11.5
                                                }
                                            ],
                                            "links": {
                                                "links": {
                                                    "first": "http://thepos.test/api/v1/products?page=1",
                                                    "last": "http://thepos.test/api/v1/products?page=1"
                                                }
                                            },
                                            "meta": {
                                                "current_page": 1,
                                                "from": 1,
                                                "last_page": 1,
                                                "path": "http://thepos.test/api/v1/products",
                                                "per_page": 15,
                                                "to": 5,
                                                "total": 5
                                            }
                                        }
                                    }
                                }
                            }
                        }
                    },
                    "401": {
                        "$ref": "#/components/responses/Error"
                    }
                },
                "parameters": [
                    {
                        "schema": {
                            "type": "integer"
                        },
                        "in": "query",
                        "name": "page",
                        "description": "page number"
                    }
                ]
            },
            "parameters": []
        },
        "/api/v2/sales-invoices": {
            "post": {
                "summary": "Create new sales invoice",
                "operationId": "SalesInvoiceController@store",
                "requestBody": {
                    "content": {
                        "application/json": {
                            "schema": {
                                "$ref": "#/components/schemas/SalesInvoice"
                            },
                            "examples": {}
                        }
                    }
                },
                "responses": {
                    "201": {
                        "description": "Created",
                        "content": {
                            "application/json": {
                                "schema": {
                                    "$ref": "#/components/schemas/SalesInvoice"
                                },
                                "examples": {
                                    "example-1": {
                                        "value": {
                                            "client_id": 0,
                                            "items": [
                                                {
                                                    "product": {
                                                        "sku": "72527273070",
                                                        "name": "UPCA prodcut",
                                                        "price": 100,
                                                        "tax_rate": 10,
                                                        "taxed_price": 110,
                                                        "image": "https://pixnio.com/media/perfume-fancy-product-package-wedding-ring",
                                                        "product_group": {
                                                            "id": 10,
                                                            "name": "products",
                                                            "parent": 1,
                                                            "is_group": false,
                                                            "disabled": true
                                                        },
                                                        "sale_price": 75,
                                                        "taxed_sale_price": 82.5,
                                                        "quantity": 0,
                                                        "available": false
                                                    },
                                                    "quantity": 1,
                                                    "selling_price": 90,
                                                    "taxed_selling_price": 99
                                                }
                                            ],
                                            "customer": {
                                                "client_id": 0,
                                                "name": "Alaa Alsalehi",
                                                "mobile_no": "05999999999",
                                                "email": "a@a.com"
                                            }
                                        }
                                    }
                                }
                            }
                        }
                    },
                    "401": {
                        "$ref": "#/components/responses/Error"
                    },
                    "404": {
                        "description": "Not Found",
                        "content": {
                            "application/json": {
                                "schema": {
                                    "$ref": "#/components/schemas/Message"
                                },
                                "examples": {
                                    "can not find product": {
                                        "value": {
                                            "code": 1,
                                            "message": "Can not find product"
                                        }
                                    }
                                }
                            }
                        }
                    },
                    "409": {
                        "description": "Already created invoice with this client id",
                        "content": {
                            "application/json": {
                                "schema": {
                                    "$ref": "#/components/schemas/Message"
                                },
                                "examples": {
                                    "example-1": {
                                        "value": {
                                            "code": 2,
                                            "message": "Already created invoice"
                                        }
                                    }
                                }
                            }
                        }
                    }
                },
                "description": ""
            },
            "parameters": []
        },
        "/api/v2/customers/": {
            "get": {
                "summary": "Get All Customers",
                "tags": [],
                "responses": {
                    "200": {
                        "$ref": "#/components/responses/CustomerPaginator"
                    },
                    "401": {
                        "$ref": "#/components/responses/Error"
                    }
                },
                "operationId": "get-api-v2-customers",
                "parameters": [
                    {
                        "schema": {
                            "type": "string"
                        },
                        "in": "query",
                        "name": "mobile_no",
                        "description": "search for customer with mobile no"
                    }
                ]
            },
            "parameters": [],
            "post": {
                "summary": "Create New Customer",
                "operationId": "post-api-v2-customers",
                "responses": {
                    "201": {
                        "description": "Created",
                        "content": {
                            "application/json": {
                                "schema": {
                                    "$ref": "#/components/schemas/Customer"
                                },
                                "examples": {
                                    "example-1": {
                                        "value": {
                                            "name": "Alaa Alsalehi",
                                            "mobile_no": "05999999999",
                                            "email": "a@a.com"
                                        }
                                    }
                                }
                            }
                        }
                    },
                    "401": {
                        "$ref": "#/components/responses/Error"
                    },
                    "409": {
                        "description": "Aleady exist customer"
                    }
                },
                "requestBody": {
                    "content": {
                        "application/json": {
                            "schema": {
                                "$ref": "#/components/schemas/Customer"
                            }
                        }
                    }
                }
            }
        }
    },
    "components": {
        "schemas": {
            "ProductPaginator": {
                "title": "ProductPaginator",
                "type": "object",
                "properties": {
                    "data": {
                        "type": "array",
                        "items": {
                            "$ref": "#/components/schemas/Product"
                        }
                    },
                    "links": {
                        "$ref": "#/components/schemas/PaginationLinks"
                    },
                    "meta": {
                        "$ref": "#/components/schemas/PaginationMeta"
                    }
                },
                "examples": [
                    {
                        "data": [
                            {
                                "sku": "72527273070",
                                "name": "UPCA prodcut",
                                "price": 100,
                                "tax_rate": 10,
                                "taxed_price": 110,
                                "image": "https://pixnio.com/media/perfume-fancy-product-package-wedding-ring",
                                "product_group": {
                                    "id": 10,
                                    "name": "products",
                                    "parent": 1,
                                    "is_group": false,
                                    "disabled": true
                                },
                                "sale_price": 75,
                                "taxed_sale_price": 82.5,
                                "quantity": 0,
                                "available": false
                            }
                        ],
                        "links": {
                            "links": {
                                "first": "http://thepos.test/api/v1/products?page=1",
                                "last": "http://thepos.test/api/v1/products?page=1"
                            }
                        },
                        "meta": {
                            "current_page": 1,
                            "from": 1,
                            "last_page": 1,
                            "path": "http://thepos.test/api/v1/products",
                            "per_page": 15,
                            "to": 5,
                            "total": 5
                        }
                    }
                ]
            },
            "PaginationLinks": {
                "title": "PaginationLinks",
                "type": "object",
                "properties": {
                    "first": {
                        "type": "string"
                    },
                    "last": {
                        "type": "string"
                    },
                    "prev": {
                        "type": [
                            "string",
                            "null"
                        ]
                    },
                    "next": {
                        "type": [
                            "string",
                            "null"
                        ]
                    }
                },
                "examples": [
                    {
                        "links": {
                            "first": "http://thepos.test/api/v1/products?page=1",
                            "last": "http://thepos.test/api/v1/products?page=1"
                        }
                    }
                ]
            },
            "PaginationMeta": {
                "title": "PaginationMeta",
                "type": "object",
                "properties": {
                    "current_page": {
                        "type": "number"
                    },
                    "from": {
                        "type": "number"
                    },
                    "last_page": {
                        "type": "number"
                    },
                    "path": {
                        "type": "string"
                    },
                    "per_page": {
                        "type": "number"
                    },
                    "to": {
                        "type": "number"
                    },
                    "total": {
                        "type": "number"
                    }
                },
                "examples": [
                    {
                        "current_page": 1,
                        "from": 1,
                        "last_page": 1,
                        "path": "http://thepos.test/api/v1/products",
                        "per_page": 15,
                        "to": 5,
                        "total": 5
                    }
                ]
            },
            "Product": {
                "title": "Product",
                "type": "object",
                "examples": [
                    {
                        "sku": "72527273070",
                        "name": "UPCA prodcut",
                        "price": 100,
                        "tax_rate": 10,
                        "taxed_price": 110,
                        "image": "https://pixnio.com/media/perfume-fancy-product-package-wedding-ring",
                        "product_group": {
                            "id": 10,
                            "name": "products",
                            "parent": 1,
                            "is_group": false,
                            "disabled": true
                        },
                        "sale_price": 75,
                        "taxed_sale_price": 82.5,
                        "quantity": 0,
                        "available": false
                    },
                    {
                        "sku": "978020137962",
                        "name": "ean13 product",
                        "price": 10,
                        "tax_rate": 15,
                        "taxed_price": 11.5,
                        "image": "https://pixnio.com/media/perfume-fancy-product-package-wedding-ring",
                        "product_group": {
                            "id": 10,
                            "name": "products",
                            "parent": 1,
                            "is_group": false,
                            "disabled": true
                        },
                        "sale_price": 5,
                        "taxed_sale_price": 5.75,
                        "quantity": 10,
                        "available": true
                    }
                ],
                "properties": {
                    "sku": {
                        "type": "string"
                    },
                    "name": {
                        "type": "string"
                    },
                    "price": {
                        "type": "number"
                    },
                    "tax_rate": {
                        "type": "number"
                    },
                    "taxed_price": {
                        "type": "number"
                    },
                    "image": {
                        "type": "string"
                    },
                    "product_group": {
                        "$ref": "#/components/schemas/ProductGroup"
                    },
                    "sale_price": {
                        "type": "number"
                    },
                    "taxed_sale_price": {
                        "type": "number"
                    },
                    "quantity": {
                        "type": "number"
                    },
                    "available": {
                        "type": "boolean"
                    }
                }
            },
            "SalesInvoiceItem": {
                "title": "Sales Invoice Item",
                "type": "object",
                "examples": [
                    {
                        "product": {
                            "sku": "72527273070",
                            "name": "UPCA prodcut",
                            "price": 100,
                            "tax_rate": 10,
                            "taxed_price": 110,
                            "image": "https://pixnio.com/media/perfume-fancy-product-package-wedding-ring",
                            "product_group": {
                                "id": 10,
                                "name": "products",
                                "parent": 1,
                                "is_group": false,
                                "disabled": true
                            },
                            "sale_price": 75,
                            "taxed_sale_price": 82.5,
                            "quantity": 0,
                            "available": false
                        },
                        "quantity": 1,
                        "selling_price": 90,
                        "taxed_selling_price": 99
                    },
                    {
                        "product": {
                            "sku": "978020137962",
                            "name": "ean13 product",
                            "price": 10,
                            "tax_rate": 15,
                            "taxed_price": 11.5,
                            "image": "https://pixnio.com/media/perfume-fancy-product-package-wedding-ring",
                            "product_group": {
                                "id": 10,
                                "name": "products",
                                "parent": 1,
                                "is_group": false,
                                "disabled": true
                            },
                            "sale_price": 5,
                            "taxed_sale_price": 5.75,
                            "quantity": 10,
                            "available": true
                        },
                        "quantity": 5,
                        "selling_price": 5,
                        "taxed_selling_price": 5.75
                    }
                ],
                "properties": {
                    "product": {
                        "$ref": "#/components/schemas/Product"
                    },
                    "quantity": {
                        "type": "number"
                    },
                    "selling_price": {
                        "type": "number"
                    },
                    "taxed_selling_price": {
                        "type": "number"
                    }
                }
            },
            "SalesInvoice": {
                "title": "SalesInvoice",
                "type": "object",
                "examples": [
                    {
                        "client_id": 0,
                        "items": [
                            {
                                "product": {
                                    "sku": "72527273070",
                                    "name": "UPCA prodcut",
                                    "price": 100,
                                    "tax_rate": 10,
                                    "taxed_price": 110,
                                    "image": "https://pixnio.com/media/perfume-fancy-product-package-wedding-ring",
                                    "product_group": {
                                        "id": 10,
                                        "name": "products",
                                        "parent": 1,
                                        "is_group": false,
                                        "disabled": true
                                    },
                                    "sale_price": 75,
                                    "taxed_sale_price": 82.5,
                                    "quantity": 0,
                                    "available": false
                                },
                                "quantity": 1,
                                "selling_price": 90,
                                "taxed_selling_price": 99
                            }
                        ],
                        "customer": {
                            "client_id": 0,
                            "name": "Alaa Alsalehi",
                            "mobile_no": "05999999999",
                            "email": "a@a.com"
                        }
                    }
                ],
                "properties": {
                    "client_id": {
                        "type": "number"
                    },
                    "items": {
                        "allOf": [
                            {
                                "items": {
                                    "$ref": "#/components/schemas/SalesInvoiceItem"
                                }
                            }
                        ],
                        "type": "array"
                    },
                    "customer": {
                        "$ref": "#/components/schemas/Customer"
                    }
                }
            },
            "Message": {
                "title": "Message",
                "type": "object",
                "properties": {
                    "code": {
                        "type": "integer"
                    },
                    "message": {
                        "type": "string"
                    }
                },
                "examples": [
                    {
                        "code": 1,
                        "message": "Can not find product"
                    }
                ]
            },
            "ProductGroup": {
                "title": "ProductGroup",
                "type": "object",
                "examples": [
                    {
                        "id": 10,
                        "name": "products",
                        "parent": 1,
                        "is_group": false,
                        "disabled": true
                    }
                ],
                "properties": {
                    "id": {
                        "type": "number"
                    },
                    "name": {
                        "type": "string"
                    },
                    "parent": {
                        "type": "number"
                    },
                    "is_group": {
                        "type": "boolean"
                    },
                    "disabled": {
                        "type": "boolean"
                    }
                }
            },
            "Customer": {
                "title": "Customer",
                "type": "object",
                "examples": [
                    {
                        "name": "Alaa Alsalehi",
                        "mobile_no": "05999999999",
                        "email": "a@a.com"
                    }
                ],
                "properties": {
                    "name": {
                        "type": "string"
                    },
                    "mobile_no": {
                        "type": "string"
                    },
                    "email": {
                        "type": [
                            "string",
                            "null"
                        ]
                    }
                },
                "required": [
                    "mobile_no"
                ]
            }
        },
        "securitySchemes": {
            "JWT": {
                "type": "http",
                "scheme": "bearer",
                "bearerFormat": "JWT"
            }
        },
        "requestBodies": {},
        "responses": {
            "CustomerPaginator": {
                "description": "Example response",
                "content": {
                    "application/json": {
                        "schema": {
                            "type": "object",
                            "properties": {
                                "data": {
                                    "type": "array",
                                    "items": {
                                        "$ref": "#/components/schemas/Customer"
                                    }
                                },
                                "links": {
                                    "$ref": "#/components/schemas/PaginationLinks"
                                },
                                "meta": {
                                    "$ref": "#/components/schemas/PaginationMeta"
                                }
                            }
                        },
                        "examples": {
                            "example": {
                                "value": {
                                    "data": [
                                        {
                                            "name": "Alaa Alsalehi",
                                            "mobile_no": "05999999999",
                                            "email": "a@a.com"
                                        }
                                    ],
                                    "links": {
                                        "links": {
                                            "first": "http://thepos.test/api/v1/products?page=1",
                                            "last": "http://thepos.test/api/v1/products?page=1"
                                        }
                                    },
                                    "meta": {
                                        "current_page": 1,
                                        "from": 1,
                                        "last_page": 1,
                                        "path": "http://thepos.test/api/v1/products",
                                        "per_page": 15,
                                        "to": 5,
                                        "total": 5
                                    }
                                }
                            }
                        }
                    }
                }
            },
            "ProductGroupPaginator": {
                "description": "Example response",
                "content": {
                    "application/json": {
                        "schema": {
                            "type": "object",
                            "properties": {
                                "data": {
                                    "type": "array",
                                    "items": {
                                        "$ref": "#/components/schemas/ProductGroup"
                                    }
                                },
                                "links": {
                                    "$ref": "#/components/schemas/PaginationLinks"
                                },
                                "meta": {
                                    "$ref": "#/components/schemas/PaginationMeta"
                                }
                            }
                        },
                        "examples": {
                            "example-1": {
                                "value": {
                                    "data": [
                                        {
                                            "id": 10,
                                            "name": "products",
                                            "parent": 1,
                                            "is_group": false,
                                            "disabled": true
                                        }
                                    ],
                                    "links": {
                                        "links": {
                                            "first": "http://thepos.test/api/v2/productGroups?page=1",
                                            "last": "http://thepos.test/api/v2/productGroups?page=1"
                                        }
                                    },
                                    "meta": {
                                        "current_page": 1,
                                        "from": 1,
                                        "last_page": 1,
                                        "path": "http://thepos.test/api/v2/productGroups",
                                        "per_page": 15,
                                        "to": 5,
                                        "total": 5
                                    }
                                }
                            }
                        }
                    }
                }
            },
            "Error": {
                "description": "Example response",
                "content": {
                    "application/json": {
                        "schema": {
                            "type": "object",
                            "properties": {
                                "code": {
                                    "type": "string"
                                },
                                "message": {
                                    "type": "string"
                                }
                            }
                        },
                        "examples": {
                            "UnauthorizedRequest": {
                                "value": {
                                    "code": "401",
                                    "message": "Unautherized request"
                                }
                            }
                        }
                    }
                },
                "headers": {}
            }
        },
        "examples": {}
    },
    "security": [
        {
            "JWT": []
        }
    ]
}
